google_photos_takeout_helper/__init__.py
google_photos_takeout_helper/__main__.py
google_photos_takeout_helper/__version__.py
google_photos_takeout_helper-2.3.0.dist-info/LICENSE
google_photos_takeout_helper-2.3.0.dist-info/METADATA
google_photos_takeout_helper-2.3.0.dist-info/WHEEL
google_photos_takeout_helper-2.3.0.dist-info/entry_points.txt
google_photos_takeout_helper-2.3.0.dist-info/top_level.txt
google_photos_takeout_helper-2.3.0.dist-info/RECORD
