Metadata-Version: 2.1
Name: google-photos-takeout-helper
Version: 2.3.0
Summary: Script that organizes the Google Photos Takeout archive into one big chronological folder
Home-page: https://github.com/TheLastGimbus/GooglePhotosTakeoutHelper/
Author: TheLastGimbus
Author-email: mateusz.soszynski@tuta.io
License: Apache
Classifier: Programming Language :: Python :: 3
Classifier: License :: OSI Approved :: Apache Software License
Classifier: Development Status :: 5 - Production/Stable
Classifier: Intended Audience :: End Users/Desktop
Classifier: Topic :: Multimedia :: Graphics
Requires-Python: >=3.6
License-File: LICENSE
Requires-Dist: piexif (==1.1.3)
Requires-Dist: win32-setctime (==1.1.0)
Requires-Dist: loguru (==0.6.0)
Requires-Dist: tqdm (==4.64.0)
